{"name":"前端学习宝库","tagline":"收藏的仓库","body":"fe-space\r\n========\r\n这个项目是为了方便前端学习而整理的。\r\n\r\n + [收藏的仓库](https://github.com/natee/fe-space/blob/master/repositories.md)    \r\n 这里包含了各种学习资料、实用技术、各种文档。\r\n + [收藏的博客](https://github.com/natee/fe-space/blob/master/ariticles.md)    \r\n 这里是收集前端（不限）国内外的文章。\r\n + [gulp实例](https://github.com/natee/fe-space/tree/master/k_gulp)    \r\n 学习gulp过程中使用的一些插件用法。\r\n + [pure css](https://github.com/natee/fe-space/tree/master/k_pure)   \r\n 学习YUI的pure css框架\r\n","google":"","note":"Don't delete this file! It's used internally to help with page regeneration."}